afex_logger/__init__.py
afex_logger/http_agent.py
afex_logger/http_interceptor.py
afex_logger/log_service.py
afex_logger/repo_service.py
afex_logger/ssm_service.py
afex_logger/tasks.py
afex_logger/util.py
afex_logger-0.1.28.dist-info/METADATA
afex_logger-0.1.28.dist-info/WHEEL
afex_logger-0.1.28.dist-info/top_level.txt
afex_logger-0.1.28.dist-info/RECORD
