Metadata-Version: 2.1
Name: afex-logger
Version: 0.1.28
Summary: AFEX logger package
Author: nlasisi@africaexchange.com
Classifier: Programming Language :: Python :: 3
Classifier: License :: OSI Approved :: MIT License
Classifier: Operating System :: OS Independent
Requires-Python: >=3.6
Requires-Dist: celery
Requires-Dist: boto3
